[{"id":1,"name":"Auriculares X900 L","description":"Auriculares Gamer JBL Quantum 600 Inalámbricos PC/PS4/PS5/Xbox/NS","price":"10000","image":"Auris.jpg","category":"Gaming","keywords":["India","Juliett","Mike"],"color":""},{"id":2,"name":"PlayStation5","description":"Consola PS5 Playstation Edición Física + Joystick Ps5 Sony Dual Sense","price":195000,"image":"Play.jpg","category":"Gaming","keywords":["Tango","India","Foxtrot","Zulu"],"color":"Maroon"},{"id":3,"name":"Mando PS5","description":"Joystick Playstation 5 Dual Sense","price":13000,"image":"Joystick.jpg","category":"Gaming","keywords":["Sierra","Alfa","Lima"],"color":"Aquamarine"},{"id":4,"name":"SpiderMan Miles Morales","description":"Juego Spiderman Miles Morales","price":"7000","image":"JuegoSpiderMan.jpg","category":"Gaming","keywords":["Echo","Oscar"],"color":""},{"id":5,"name":"Teclado XRT20","description":"Teclado Genius Smart XRT-20 Negro","price":1500,"image":"Teclado.jpg","category":"Accesorios","keywords":["Foxtrot","Charlie","Lima","Uniform","Papa"],"color":"Maroon"},{"id":6,"name":"Silla Gaming Champ","description":"Silla Gamer Makkax Roja/Blanca/Negra","price":38200,"image":"Silla.jpg","category":"Accesorios","keywords":["Zulu","X-ray"],"color":"Fuscia"},{"id":7,"name":"Mouse Logitech 400","description":"Mouse Gamer Optico Colores Gaming Rgb","price":2000,"image":"Mouse.jpg","category":"Accesorios","keywords":["Whiskey","Tango","Delta","Lima","Victor"],"color":"Fuscia"},{"id":8,"name":"MousePad Alien XR","description":"Mouse Pad Razer Firefly V2 Hard Surface Chroma RGB 35x28x3mm","price":4000,"image":"Mousepad.jpg","category":"Accesorios","keywords":["Golf","Papa","Alfa","Juliett"],"color":"Crimson"},{"id":9,"name":"Tablet Samsung X10","description":"Tablet Samsung Galaxy Tab A7 SM-T500 10.4 64GB dark gray con 3GB de memoria RAM","price":30000,"image":"Tablet.jpg","category":"Dispositivos","keywords":["Mike","Charlie","Charlie"],"color":"Crimson"},{"id":10,"name":"Notebook Lenovo 809","description":"Notebook Lenovo Yoga 7 Core I7 12GB SSD 512GB TACTIL Win10","price":80000,"image":"Notebook.jpg","category":"Dispositivos","keywords":["Sierra","Victor","Sierra"],"color":"Puce"},{"id":11,"name":"Samsung Galaxy S10","description":"Celular Libre Samsung Galaxy S10 Violeta SM-G991BZVLARO CM","price":120000,"image":"Celular.jpg","category":"Dispositivos","keywords":["Echo","Zulu","India","Zulu"],"color":"Purple"},{"id":12,"name":"Tablet LG Flex","description":"ThinkPad X1 Fold Gen 1 - Black 8 GB LPDDR4x 4266MHz Soldada, POP Memoria","price":150000,"image":"TabletPlegable.jpg","category":"Dispositivos","keywords":["Lima","Charlie"],"color":"Violet"}]